cindi/__init__.py
cindi/cindi.py
cindi/cindi_tests.py
cindi-0.9.1.3.dist-info/METADATA
cindi-0.9.1.3.dist-info/WHEEL
cindi-0.9.1.3.dist-info/licenses/LICENSE
cindi-0.9.1.3.dist-info/RECORD
