Metadata-Version: 2.1
Name: cindi
Version: 0.9.1.3
Summary: CINDI is a Meta-DBMS to support rapid application prototyping.
Project-URL: Homepage, https://github.com/ultasun/cindi
Project-URL: Bug Tracker, https://github.com/ultasun/cindi/issues
Author-email: ultasun <ultasun@icloud.com>
License: Copyright (c) 2022, ultasun. All rights reserved.
Classifier: Development Status :: 3 - Alpha
Classifier: Environment :: Console
Classifier: Framework :: Flask
Classifier: License :: OSI Approved :: BSD License
Classifier: Operating System :: OS Independent
Classifier: Programming Language :: Python :: 3
Classifier: Programming Language :: SQL
Classifier: Topic :: Database :: Database Engines/Servers
Classifier: Topic :: Database :: Front-Ends
Classifier: Topic :: Internet :: WWW/HTTP :: HTTP Servers
Classifier: Topic :: Software Development :: Code Generators
Classifier: Topic :: Software Development :: Interpreters
Requires-Python: >=3.0
Requires-Dist: flask
Requires-Dist: flask-cors
Requires-Dist: pyopenssl
Provides-Extra: mongodb
Requires-Dist: pymongo; extra == 'mongodb'
Provides-Extra: mysql
Requires-Dist: mysql-connector-python; extra == 'mysql'
Provides-Extra: postgres
Requires-Dist: psycopg; extra == 'postgres'
Provides-Extra: redis
Requires-Dist: redis; extra == 'redis'
